[
    {
        "cognome": "Albergoni",
        "comunasc": "58091",
        "datanasc": "1973-08-25",
        "id": "833",
        "nome": "Adriano",
        "sesso": "M"
    },
    {
        "cognome": "Alberoni",
        "comunasc": "56021",
        "datanasc": "1967-12-03",
        "id": "1628",
        "nome": "Alberto",
        "sesso": "M"
    },
    {
        "cognome": "Albertoni",
        "comunasc": "58091",
        "datanasc": "1956-03-01",
        "id": "2484",
        "nome": "Aldo",
        "sesso": "M"
    },
    {
        "cognome": "Alberzoni",
        "comunasc": "58091",
        "datanasc": "1965-05-22",
        "id": "619",
        "nome": "Alessandra",
        "sesso": "F"
    },
    {
        "cognome": "Albignoni",
        "comunasc": "56021",
        "datanasc": "1947-05-05",
        "id": "1192",
        "nome": "Alessia",
        "sesso": "F"
    },
    {
        "cognome": "Albioni",
        "comunasc": "58091",
        "datanasc": "1974-07-19",
        "id": "621",
        "nome": "Alfio",
        "sesso": "M"
    },
    {
        "cognome": "Alboni",
        "comunasc": "58091",
        "datanasc": "1972-07-30",
        "id": "2327",
        "nome": "Alfonso",
        "sesso": "M"
    },
    {
        "cognome": "Albrigoni",
        "comunasc": "58091",
        "datanasc": "1966-01-05",
        "id": "680",
        "nome": "Alfredo",
        "sesso": "M"
    },
    {
        "cognome": "Bertaboni",
        "comunasc": "56016",
        "datanasc": "1935-07-16",
        "id": "2620",
        "nome": "Alvaro",
        "sesso": "M"
    },
    {
        "cognome": "Bertamoni",
        "comunasc": "56059",
        "datanasc": "1976-01-30",
        "id": "3369",
        "nome": "Amedeo",
        "sesso": "M"
    },
    {
        "cognome": "Bertazoni",
        "comunasc": "56016",
        "datanasc": "1935-07-16",
        "id": "3571",
        "nome": "Amerigo",
        "sesso": "M"
    },
    {
        "cognome": "Bertazzoni",
        "comunasc": "58091",
        "datanasc": "1961-02-03",
        "id": "2132",
        "nome": "Anacleto",
        "sesso": "M"
    },
    {
        "cognome": "Bertelloni",
        "comunasc": "58091",
        "datanasc": "1975-09-07",
        "id": "1064",
        "nome": "Angela",
        "sesso": "F"
    },
    {
        "cognome": "Bertiboni",
        "comunasc": "56059",
        "datanasc": "1949-03-25",
        "id": "2884",
        "nome": "Anselmo",
        "sesso": "M"
    },
    {
        "cognome": "Bertoleoni",
        "comunasc": "58091",
        "datanasc": "1958-03-08",
        "id": "2232",
        "nome": "Antonella",
        "sesso": "F"
    },
    {
        "cognome": "Bertoloni",
        "comunasc": "56059",
        "datanasc": "1979-02-24",
        "id": "4218",
        "nome": "Antonio",
        "sesso": "M"
    },
    {
        "cognome": "Bertoni",
        "comunasc": "56059",
        "datanasc": "1949-02-14",
        "id": "513",
        "nome": "Antonio",
        "sesso": "M"
    },
    {
        "cognome": "Calandroni",
        "comunasc": "58091",
        "datanasc": "1956-08-31",
        "id": "617",
        "nome": "Arcangelo",
        "sesso": "M"
    },
    {
        "cognome": "Calantoni",
        "comunasc": "60002",
        "datanasc": "1951-03-04",
        "id": "1811",
        "nome": "Arduino",
        "sesso": "M"
    },
    {
        "cognome": "Calatroni",
        "comunasc": "60087",
        "datanasc": "1963-06-13",
        "id": "1874",
        "nome": "Armando",
        "sesso": "M"
    },
    {
        "cognome": "Albergoni",
        "comunasc": "58091",
        "datanasc": "1973-08-25",
        "id": "833",
        "nome": "Adriano",
        "sesso": "M"
    },
    {
        "cognome": "Alberoni",
        "comunasc": "56021",
        "datanasc": "1967-12-03",
        "id": "1628",
        "nome": "Alberto",
        "sesso": "M"
    },
    {
        "cognome": "Albertoni",
        "comunasc": "58091",
        "datanasc": "1956-03-01",
        "id": "2484",
        "nome": "Aldo",
        "sesso": "M"
    },
    {
        "cognome": "Alberzoni",
        "comunasc": "58091",
        "datanasc": "1965-05-22",
        "id": "619",
        "nome": "Alessandra",
        "sesso": "F"
    },
    {
        "cognome": "Albignoni",
        "comunasc": "56021",
        "datanasc": "1947-05-05",
        "id": "1192",
        "nome": "Alessia",
        "sesso": "F"
    },
    {
        "cognome": "Albioni",
        "comunasc": "58091",
        "datanasc": "1974-07-19",
        "id": "621",
        "nome": "Alfio",
        "sesso": "M"
    },
    {
        "cognome": "Alboni",
        "comunasc": "58091",
        "datanasc": "1972-07-30",
        "id": "2327",
        "nome": "Alfonso",
        "sesso": "M"
    },
    {
        "cognome": "Albrigoni",
        "comunasc": "58091",
        "datanasc": "1966-01-05",
        "id": "680",
        "nome": "Alfredo",
        "sesso": "M"
    },
    {
        "cognome": "Bertaboni",
        "comunasc": "56016",
        "datanasc": "1935-07-16",
        "id": "2620",
        "nome": "Alvaro",
        "sesso": "M"
    },
    {
        "cognome": "Bertamoni",
        "comunasc": "56059",
        "datanasc": "1976-01-30",
        "id": "3369",
        "nome": "Amedeo",
        "sesso": "M"
    },
    {
        "cognome": "Bertazoni",
        "comunasc": "56016",
        "datanasc": "1935-07-16",
        "id": "3571",
        "nome": "Amerigo",
        "sesso": "M"
    },
    {
        "cognome": "Bertazzoni",
        "comunasc": "58091",
        "datanasc": "1961-02-03",
        "id": "2132",
        "nome": "Anacleto",
        "sesso": "M"
    },
    {
        "cognome": "Bertelloni",
        "comunasc": "58091",
        "datanasc": "1975-09-07",
        "id": "1064",
        "nome": "Angela",
        "sesso": "F"
    },
    {
        "cognome": "Bertiboni",
        "comunasc": "56059",
        "datanasc": "1949-03-25",
        "id": "2884",
        "nome": "Anselmo",
        "sesso": "M"
    },
    {
        "cognome": "Bertoleoni",
        "comunasc": "58091",
        "datanasc": "1958-03-08",
        "id": "2232",
        "nome": "Antonella",
        "sesso": "F"
    },
    {
        "cognome": "Bertoloni",
        "comunasc": "56059",
        "datanasc": "1979-02-24",
        "id": "4218",
        "nome": "Antonio",
        "sesso": "M"
    },
    {
        "cognome": "Bertoni",
        "comunasc": "56059",
        "datanasc": "1949-02-14",
        "id": "513",
        "nome": "Antonio",
        "sesso": "M"
    },
    {
        "cognome": "Calandroni",
        "comunasc": "58091",
        "datanasc": "1956-08-31",
        "id": "617",
        "nome": "Arcangelo",
        "sesso": "M"
    },
    {
        "cognome": "Calantoni",
        "comunasc": "60002",
        "datanasc": "1951-03-04",
        "id": "1811",
        "nome": "Arduino",
        "sesso": "M"
    },
    {
        "cognome": "Calatroni",
        "comunasc": "60087",
        "datanasc": "1963-06-13",
        "id": "1874",
        "nome": "Armando",
        "sesso": "M"
    }
]